cpsmehelper/__init__.py
cpsmehelper/colors.py
cpsmehelper/export.py
cpsmehelper-1.0.1.dist-info/METADATA
cpsmehelper-1.0.1.dist-info/WHEEL
cpsmehelper-1.0.1.dist-info/licenses/LICENSE
cpsmehelper-1.0.1.dist-info/RECORD
