Metadata-Version: 2.3
Name: cpsmehelper
Version: 1.0.1
Summary: Helper functions of the CPSME TU Berlin
Author-email: Merten Stender <merten.stender@tu-berlin.de>
License-File: LICENSE
Classifier: License :: OSI Approved :: MIT License
Classifier: Operating System :: OS Independent
Classifier: Programming Language :: Python :: 3
Requires-Python: >=3.7
Requires-Dist: matplotlib>=3.5.0
Requires-Dist: numpy>=1.18
Requires-Dist: tikzplotlib>=0.10.1
